<?xml version="1.0" encoding="UTF-8"?>
<!DOCTYPE mapper PUBLIC "-//mybatis.org//DTD Mapper 3.0//EN" "http://mybatis.org/dtd/mybatis-3-mapper.dtd">
<mapper namespace="team.softwarede.confersys.mapper.MeetingRoomMapper">
  <resultMap id="BaseResultMap" type="team.softwarede.confersys.entity.MeetingRoom">
    <!--
      WARNING - @mbg.generated
      This element is automatically generated by MyBatis Generator, do not modify.
      This element was generated on Thu May 30 09:12:43 CST 2019.
    -->
    <id column="id" jdbcType="INTEGER" property="id" />
    <result column="capacity" jdbcType="INTEGER" property="capacity" />
    <result column="room_introduce" jdbcType="VARCHAR" property="roomIntroduce" />
    <result column="room_number" jdbcType="VARCHAR" property="roomNumber" />
    <result column="building" jdbcType="VARCHAR" property="building" />
    <result column="floor" jdbcType="INTEGER" property="floor" />
    <result column="status_id" jdbcType="CHAR" property="statusId" />
  </resultMap>
  <sql id="Base_Column_List">
    <!--
      WARNING - @mbg.generated
      This element is automatically generated by MyBatis Generator, do not modify.
      This element was generated on Thu May 30 09:12:43 CST 2019.
    -->
    id, capacity, room_introduce, room_number, building, floor, status_id
  </sql>
  <select id="selectByPrimaryKey" parameterType="java.lang.Integer" resultMap="BaseResultMap">
    <!--
      WARNING - @mbg.generated
      This element is automatically generated by MyBatis Generator, do not modify.
      This element was generated on Thu May 30 09:12:43 CST 2019.
    -->
    select 
    <include refid="Base_Column_List" />
    from meeting_room
    where id = #{id,jdbcType=INTEGER}
  </select>
  <delete id="deleteByPrimaryKey" parameterType="java.lang.Integer">
    <!--
      WARNING - @mbg.generated
      This element is automatically generated by MyBatis Generator, do not modify.
      This element was generated on Thu May 30 09:12:43 CST 2019.
    -->
    delete from meeting_room
    where id = #{id,jdbcType=INTEGER}
  </delete>
  <insert id="insert" parameterType="team.softwarede.confersys.entity.MeetingRoom">
    <!--
      WARNING - @mbg.generated
      This element is automatically generated by MyBatis Generator, do not modify.
      This element was generated on Thu May 30 09:12:43 CST 2019.
    -->
    insert into meeting_room (id, capacity, room_introduce, 
      room_number, building, floor, 
      status_id)
    values (#{id,jdbcType=INTEGER}, #{capacity,jdbcType=INTEGER}, #{roomIntroduce,jdbcType=VARCHAR}, 
      #{roomNumber,jdbcType=VARCHAR}, #{building,jdbcType=VARCHAR}, #{floor,jdbcType=INTEGER}, 
      #{statusId,jdbcType=CHAR})
  </insert>
  <insert id="insertSelective" parameterType="team.softwarede.confersys.entity.MeetingRoom">
    <!--
      WARNING - @mbg.generated
      This element is automatically generated by MyBatis Generator, do not modify.
      This element was generated on Thu May 30 09:12:43 CST 2019.
    -->
    insert into meeting_room
    <trim prefix="(" suffix=")" suffixOverrides=",">
      <if test="id != null">
        id,
      </if>
      <if test="capacity != null">
        capacity,
      </if>
      <if test="roomIntroduce != null">
        room_introduce,
      </if>
      <if test="roomNumber != null">
        room_number,
      </if>
      <if test="building != null">
        building,
      </if>
      <if test="floor != null">
        floor,
      </if>
      <if test="statusId != null">
        status_id,
      </if>
    </trim>
    <trim prefix="values (" suffix=")" suffixOverrides=",">
      <if test="id != null">
        #{id,jdbcType=INTEGER},
      </if>
      <if test="capacity != null">
        #{capacity,jdbcType=INTEGER},
      </if>
      <if test="roomIntroduce != null">
        #{roomIntroduce,jdbcType=VARCHAR},
      </if>
      <if test="roomNumber != null">
        #{roomNumber,jdbcType=VARCHAR},
      </if>
      <if test="building != null">
        #{building,jdbcType=VARCHAR},
      </if>
      <if test="floor != null">
        #{floor,jdbcType=INTEGER},
      </if>
      <if test="statusId != null">
        #{statusId,jdbcType=CHAR},
      </if>
    </trim>
  </insert>
  <update id="updateByPrimaryKeySelective" parameterType="team.softwarede.confersys.entity.MeetingRoom">
    <!--
      WARNING - @mbg.generated
      This element is automatically generated by MyBatis Generator, do not modify.
      This element was generated on Thu May 30 09:12:43 CST 2019.
    -->
    update meeting_room
    <set>
      <if test="capacity != null">
        capacity = #{capacity,jdbcType=INTEGER},
      </if>
      <if test="roomIntroduce != null">
        room_introduce = #{roomIntroduce,jdbcType=VARCHAR},
      </if>
      <if test="roomNumber != null">
        room_number = #{roomNumber,jdbcType=VARCHAR},
      </if>
      <if test="building != null">
        building = #{building,jdbcType=VARCHAR},
      </if>
      <if test="floor != null">
        floor = #{floor,jdbcType=INTEGER},
      </if>
      <if test="statusId != null">
        status_id = #{statusId,jdbcType=CHAR},
      </if>
    </set>
    where id = #{id,jdbcType=INTEGER}
  </update>
  <update id="updateByPrimaryKey" parameterType="team.softwarede.confersys.entity.MeetingRoom">
    <!--
      WARNING - @mbg.generated
      This element is automatically generated by MyBatis Generator, do not modify.
      This element was generated on Thu May 30 09:12:43 CST 2019.
    -->
    update meeting_room
    set capacity = #{capacity,jdbcType=INTEGER},
      room_introduce = #{roomIntroduce,jdbcType=VARCHAR},
      room_number = #{roomNumber,jdbcType=VARCHAR},
      building = #{building,jdbcType=VARCHAR},
      floor = #{floor,jdbcType=INTEGER},
      status_id = #{statusId,jdbcType=CHAR}
    where id = #{id,jdbcType=INTEGER}
  </update>
</mapper>